gress/__init__.py
gress/bar.py
gress/enums.py
gress/prebuilds.py
gress/utils.py
gress/widgets.py
gress-0.4.1.dist-info/LICENSE
gress-0.4.1.dist-info/METADATA
gress-0.4.1.dist-info/WHEEL
gress-0.4.1.dist-info/top_level.txt
gress-0.4.1.dist-info/RECORD
