Metadata-Version: 2.1
Name: gress
Version: 0.4.1
Summary: Gress - Naive progress monitor
Home-page: https://github.com/xxao/gress
Author: Martin Strohalm
Author-email: 
License: MIT
Platform: UNKNOWN
Classifier: Development Status :: 3 - Alpha
Classifier: Programming Language :: Python :: 3 :: Only
Classifier: Operating System :: OS Independent
Classifier: Topic :: Utilities
License-File: LICENSE
